{
    "sky_color": "0x000000",
    "items": [],
    "groups": [
        {
            "x": 0,
            "y": 0,
            "z": 0,
            "kind": "fixed",
            "platforms": [
                {
                    "x": -2.5,
                    "y": 0,
                    "z": -0.5,
                    "w": 5,
                    "h": 1,
                    "d": 1,
                    "material": 11
                }
            ]
        }
    ],
    "spawn": {
        "x": 0,
        "y": 5,
        "z": 0
    }
}